<?xml version="1.0" encoding="UTF-8"?>

<!-- generated on 2024-10-22 10:59:51.897576 by randomTrips.py UNKNOWN
<configuration>
    <net-file value="/opt/homebrew/opt/sumo/share/sumo/tools/2024-10-08-17-29-51/241018_A034.net.xml"/>
    <route-file value="241022_random_route_bicycles.rou.xml"/>
    <prefix value="bike"/>
    <vehicle-class value="bicycle"/>
    <verbose value="True"/>
    <insertion-density value="70.0"/>
    <random-depart value="True"/>
</configuration>
-->

<routes xmlns:xsi="http://www.w3.org/2001/XMLSchema-instance" xsi:noNamespaceSchemaLocation="http://sumo.dlr.de/xsd/routes_file.xsd">
    <vType id="bike_bicycle" vClass="bicycle"/>
    <trip id="bike0" depart="1.36" from="700236092#1" to="-23015831" type="bike_bicycle"/>
    <trip id="bike1" depart="2.99" from="4195580#2" to="23508141#0" type="bike_bicycle"/>
    <trip id="bike2" depart="10.21" from="75392301#1" to="-881694399" type="bike_bicycle"/>
    <trip id="bike3" depart="14.34" from="150032770#0" to="-4144040#3" type="bike_bicycle"/>
    <trip id="bike4" depart="29.86" from="-378479743#0" to="700236092#0" type="bike_bicycle"/>
    <trip id="bike5" depart="33.63" from="150041579#0" to="4019053#2" type="bike_bicycle"/>
    <trip id="bike6" depart="41.14" from="4019053#2" to="378479743#0" type="bike_bicycle"/>
    <trip id="bike7" depart="50.14" from="-150032770#1" to="53207959#1" type="bike_bicycle"/>
    <trip id="bike8" depart="56.67" from="-624481020#3" to="-23508224" type="bike_bicycle"/>
    <trip id="bike9" depart="57.23" from="35574708#1" to="-150041594#1" type="bike_bicycle"/>
    <trip id="bike10" depart="60.64" from="506015829#1" to="-4195580#2" type="bike_bicycle"/>
    <trip id="bike11" depart="70.54" from="-484022097" to="700440129" type="bike_bicycle"/>
    <trip id="bike12" depart="79.43" from="-881694399" to="-378479743#3" type="bike_bicycle"/>
    <trip id="bike13" depart="79.73" from="700440138" to="-1265069358#1" type="bike_bicycle"/>
    <trip id="bike14" depart="83.68" from="700236093" to="-378479743#2" type="bike_bicycle"/>
    <trip id="bike15" depart="84.24" from="-378479743#2" to="-56163443#3" type="bike_bicycle"/>
    <trip id="bike16" depart="86.31" from="-4144040#4" to="4019053#2" type="bike_bicycle"/>
    <trip id="bike17" depart="101.10" from="-150032770#2" to="-1290085526#1" type="bike_bicycle"/>
    <trip id="bike18" depart="102.13" from="56163443#1" to="-51873805" type="bike_bicycle"/>
    <trip id="bike19" depart="105.79" from="-715835444#5" to="-4144040#1" type="bike_bicycle"/>
    <trip id="bike20" depart="111.49" from="-150041551#3" to="449551311" type="bike_bicycle"/>
    <trip id="bike21" depart="117.35" from="23248109#1" to="44973978" type="bike_bicycle"/>
    <trip id="bike22" depart="127.67" from="150041594#0" to="53207959#0" type="bike_bicycle"/>
    <trip id="bike23" depart="130.98" from="23015831" to="-23248109#1" type="bike_bicycle"/>
    <trip id="bike24" depart="133.87" from="214812786" to="715835444#3" type="bike_bicycle"/>
    <trip id="bike25" depart="147.08" from="-150041551#0" to="53207959#1" type="bike_bicycle"/>
    <trip id="bike26" depart="151.01" from="700440129" to="214812788#2" type="bike_bicycle"/>
    <trip id="bike27" depart="156.24" from="150041579#2" to="715913363#2" type="bike_bicycle"/>
    <trip id="bike28" depart="162.83" from="-150041594#1" to="150041580" type="bike_bicycle"/>
    <trip id="bike29" depart="163.22" from="150032770#1" to="4144040#4" type="bike_bicycle"/>
    <trip id="bike30" depart="163.87" from="196656222#1" to="700440139" type="bike_bicycle"/>
    <trip id="bike31" depart="164.49" from="-196656222#1" to="-196656222#0" type="bike_bicycle"/>
    <trip id="bike32" depart="164.66" from="378479743#6" to="-150041565" type="bike_bicycle"/>
    <trip id="bike33" depart="178.64" from="-700440130#1" to="378479753" type="bike_bicycle"/>
    <trip id="bike34" depart="181.87" from="23508224" to="-70205228#2" type="bike_bicycle"/>
    <trip id="bike35" depart="185.17" from="E2" to="23015831" type="bike_bicycle"/>
    <trip id="bike36" depart="186.73" from="150041579#0" to="378479743#2" type="bike_bicycle"/>
    <trip id="bike37" depart="188.30" from="-23248109#1" to="4195580#2" type="bike_bicycle"/>
    <trip id="bike38" depart="189.61" from="700236092#1" to="395456769#0" type="bike_bicycle"/>
    <trip id="bike39" depart="192.27" from="51873805" to="4295817#1" type="bike_bicycle"/>
    <trip id="bike40" depart="200.19" from="-484022097" to="150041551#1" type="bike_bicycle"/>
    <trip id="bike41" depart="205.31" from="-60263960" to="-715835444#2" type="bike_bicycle"/>
    <trip id="bike42" depart="205.50" from="150041579#0" to="150032770#0" type="bike_bicycle"/>
    <trip id="bike43" depart="205.91" from="-23248109#1" to="150032770#2" type="bike_bicycle"/>
    <trip id="bike44" depart="207.19" from="4144040#3" to="103958941#2" type="bike_bicycle"/>
    <trip id="bike45" depart="210.02" from="-378479743#6" to="70205228#1" type="bike_bicycle"/>
    <trip id="bike46" depart="229.80" from="-196656222#0" to="624481020#2" type="bike_bicycle"/>
    <trip id="bike47" depart="237.91" from="-23248109#0" to="-23015831" type="bike_bicycle"/>
    <trip id="bike48" depart="239.38" from="484022097" to="59591195#2" type="bike_bicycle"/>
    <trip id="bike49" depart="240.71" from="254075881#1" to="35574708#1" type="bike_bicycle"/>
    <trip id="bike50" depart="241.70" from="35574708#1" to="-715835444#1" type="bike_bicycle"/>
    <trip id="bike51" depart="246.68" from="-378479743#1" to="-715835444#5" type="bike_bicycle"/>
    <trip id="bike52" depart="248.45" from="4144040#3" to="484022097" type="bike_bicycle"/>
    <trip id="bike53" depart="249.90" from="700440129" to="4295817#1" type="bike_bicycle"/>
    <trip id="bike54" depart="258.85" from="73372559" to="378479743#1" type="bike_bicycle"/>
    <trip id="bike55" depart="260.68" from="116556688" to="254075881#1" type="bike_bicycle"/>
    <trip id="bike56" depart="262.26" from="-484022097" to="395456769#1" type="bike_bicycle"/>
    <trip id="bike57" depart="263.77" from="-56163443#3" to="-23248109#1" type="bike_bicycle"/>
    <trip id="bike58" depart="267.60" from="700236092#0" to="103958941#0" type="bike_bicycle"/>
    <trip id="bike59" depart="271.93" from="506015829#1" to="24509268" type="bike_bicycle"/>
    <trip id="bike60" depart="276.62" from="59591195#2" to="700236092#0" type="bike_bicycle"/>
    <trip id="bike61" depart="278.19" from="75392301#0" to="60263960" type="bike_bicycle"/>
    <trip id="bike62" depart="280.25" from="378479753" to="395456768" type="bike_bicycle"/>
    <trip id="bike63" depart="280.29" from="-150032770#2" to="70205228#2" type="bike_bicycle"/>
    <trip id="bike64" depart="284.90" from="624481020#2" to="-624481020#1" type="bike_bicycle"/>
    <trip id="bike65" depart="284.96" from="-4195580#0" to="4195580#2" type="bike_bicycle"/>
    <trip id="bike66" depart="290.97" from="-715835444#2" to="-715835444#2" type="bike_bicycle"/>
    <trip id="bike67" depart="291.51" from="-1290085526#1" to="700440129" type="bike_bicycle"/>
    <trip id="bike68" depart="292.46" from="35574708#1" to="1290085525#1" type="bike_bicycle"/>
    <trip id="bike69" depart="292.96" from="-378479743#4" to="378479753" type="bike_bicycle"/>
    <trip id="bike70" depart="297.04" from="-150032770#5" to="44973978" type="bike_bicycle"/>
    <trip id="bike71" depart="298.43" from="-484022097" to="150032770#1" type="bike_bicycle"/>
    <trip id="bike72" depart="300.29" from="103958941#2" to="103958941#2" type="bike_bicycle"/>
    <trip id="bike73" depart="302.47" from="43135644#0" to="53207959#0" type="bike_bicycle"/>
    <trip id="bike74" depart="306.60" from="378479740#1" to="-196656222#1" type="bike_bicycle"/>
    <trip id="bike75" depart="308.29" from="-150041551#3" to="-378479743#5" type="bike_bicycle"/>
    <trip id="bike76" depart="322.24" from="38115188" to="4144040#2" type="bike_bicycle"/>
    <trip id="bike77" depart="323.57" from="-700440130#0" to="4019053#2" type="bike_bicycle"/>
    <trip id="bike78" depart="326.71" from="196656222#0" to="150041551#0" type="bike_bicycle"/>
    <trip id="bike79" depart="329.57" from="-700440130#1" to="492925919" type="bike_bicycle"/>
    <trip id="bike80" depart="332.41" from="-23508224" to="150032770#2" type="bike_bicycle"/>
    <trip id="bike81" depart="335.69" from="-700440136" to="4144040#3" type="bike_bicycle"/>
    <trip id="bike82" depart="335.92" from="196656222#0" to="4144040#1" type="bike_bicycle"/>
    <trip id="bike83" depart="347.63" from="-150041551#1" to="1290085525#0" type="bike_bicycle"/>
    <trip id="bike84" depart="369.53" from="378479743#4" to="-1265069360#0" type="bike_bicycle"/>
    <trip id="bike85" depart="372.30" from="-715835444#1" to="-4195580#2" type="bike_bicycle"/>
    <trip id="bike86" depart="378.42" from="-378479743#3" to="-60263960" type="bike_bicycle"/>
    <trip id="bike87" depart="379.56" from="-881694399" to="-1265069360#0" type="bike_bicycle"/>
    <trip id="bike88" depart="383.23" from="492925920#0" to="-4144040#1" type="bike_bicycle"/>
    <trip id="bike89" depart="396.41" from="1290085525#1" to="4195580#2" type="bike_bicycle"/>
    <trip id="bike90" depart="397.17" from="214812786" to="624481020#4" type="bike_bicycle"/>
    <trip id="bike91" depart="397.44" from="59591195#2" to="-150041594#1" type="bike_bicycle"/>
    <trip id="bike92" depart="408.18" from="700440128" to="-150032770#6" type="bike_bicycle"/>
    <trip id="bike93" depart="411.33" from="-150032770#1" to="70205228#0" type="bike_bicycle"/>
    <trip id="bike94" depart="411.91" from="700440128" to="254075881#1" type="bike_bicycle"/>
    <trip id="bike95" depart="413.56" from="378479743#0" to="4195610#2" type="bike_bicycle"/>
    <trip id="bike96" depart="420.27" from="150032770#6" to="-23508141#0" type="bike_bicycle"/>
    <trip id="bike97" depart="421.06" from="-150032770#1" to="-70205228#2" type="bike_bicycle"/>
    <trip id="bike98" depart="428.78" from="59591195#1" to="378479743#4" type="bike_bicycle"/>
    <trip id="bike99" depart="432.86" from="624481020#2" to="70205228#0" type="bike_bicycle"/>
    <trip id="bike100" depart="435.31" from="-23015831" to="700236092#0" type="bike_bicycle"/>
    <trip id="bike101" depart="436.31" from="-624481020#3" to="378479740#1" type="bike_bicycle"/>
    <trip id="bike102" depart="438.45" from="23248109#1" to="1290085525#0" type="bike_bicycle"/>
    <trip id="bike103" depart="442.62" from="-715835444#2" to="-715835444#2" type="bike_bicycle"/>
    <trip id="bike104" depart="447.31" from="-881694399" to="-4144040#0" type="bike_bicycle"/>
    <trip id="bike105" depart="449.61" from="214812788#2" to="-23508141#0" type="bike_bicycle"/>
    <trip id="bike106" depart="456.89" from="214812788#2" to="700440139" type="bike_bicycle"/>
    <trip id="bike107" depart="458.77" from="116556686#1" to="4295817#3" type="bike_bicycle"/>
    <trip id="bike108" depart="464.09" from="624481020#0" to="59591195#2" type="bike_bicycle"/>
    <trip id="bike109" depart="467.24" from="-624481020#1" to="-378479743#3" type="bike_bicycle"/>
    <trip id="bike110" depart="469.06" from="-4295817#0" to="378479743#1" type="bike_bicycle"/>
    <trip id="bike111" depart="469.88" from="506013711#1" to="395456769#1" type="bike_bicycle"/>
    <trip id="bike112" depart="470.27" from="-4144040#4" to="506015829#1" type="bike_bicycle"/>
    <trip id="bike113" depart="471.07" from="196656222#1" to="492925919" type="bike_bicycle"/>
    <trip id="bike114" depart="472.18" from="506013711#1" to="150041551#1" type="bike_bicycle"/>
    <trip id="bike115" depart="475.35" from="70205228#1" to="23508224" type="bike_bicycle"/>
    <trip id="bike116" depart="477.86" from="395456769#1" to="378479743#5" type="bike_bicycle"/>
    <trip id="bike117" depart="481.27" from="700440128" to="378479743#6" type="bike_bicycle"/>
    <trip id="bike118" depart="489.66" from="-378479743#6" to="-150041594#1" type="bike_bicycle"/>
    <trip id="bike119" depart="494.30" from="150041565" to="-700440130#1" type="bike_bicycle"/>
    <trip id="bike120" depart="497.55" from="-700440130#1" to="-150041551#3" type="bike_bicycle"/>
    <trip id="bike121" depart="497.86" from="214812788#2" to="-700440136" type="bike_bicycle"/>
    <trip id="bike122" depart="510.66" from="150041579#0" to="-150041551#3" type="bike_bicycle"/>
    <trip id="bike123" depart="517.31" from="624481020#2" to="-182982119#1" type="bike_bicycle"/>
    <trip id="bike124" depart="518.49" from="700440128" to="700236093" type="bike_bicycle"/>
    <trip id="bike125" depart="521.52" from="378479753" to="196656222#1" type="bike_bicycle"/>
    <trip id="bike126" depart="522.10" from="150041580" to="23508142#0" type="bike_bicycle"/>
    <trip id="bike127" depart="522.19" from="56163443#1" to="700440137" type="bike_bicycle"/>
    <trip id="bike128" depart="525.49" from="150041578" to="59591195#1" type="bike_bicycle"/>
    <trip id="bike129" depart="541.15" from="4144040#1" to="-70205228#1" type="bike_bicycle"/>
    <trip id="bike130" depart="546.20" from="150041594#0" to="-378479743#4" type="bike_bicycle"/>
    <trip id="bike131" depart="555.28" from="-182982119#1" to="-23248109#0" type="bike_bicycle"/>
    <trip id="bike132" depart="555.71" from="700440137" to="-715835444#3" type="bike_bicycle"/>
    <trip id="bike133" depart="560.76" from="4295817#3" to="196656222#1" type="bike_bicycle"/>
    <trip id="bike134" depart="566.65" from="-4144040#4" to="-56163443#3" type="bike_bicycle"/>
    <trip id="bike135" depart="571.46" from="150041551#2" to="150032770#6" type="bike_bicycle"/>
    <trip id="bike136" depart="574.86" from="23248109#1" to="-378479743#5" type="bike_bicycle"/>
    <trip id="bike137" depart="585.34" from="1290085525#0" to="-689912267#0" type="bike_bicycle"/>
    <trip id="bike138" depart="596.40" from="150032770#2" to="-715835444#2" type="bike_bicycle"/>
    <trip id="bike139" depart="603.64" from="378479743#4" to="53207959#3" type="bike_bicycle"/>
    <trip id="bike140" depart="604.89" from="4144040#0" to="-150041565" type="bike_bicycle"/>
    <trip id="bike141" depart="606.26" from="-23248109#1" to="4144040#3" type="bike_bicycle"/>
    <trip id="bike142" depart="608.60" from="-70205228#0" to="4295817#1" type="bike_bicycle"/>
    <trip id="bike143" depart="610.76" from="4144040#2" to="700440139" type="bike_bicycle"/>
    <trip id="bike144" depart="621.01" from="700440130#0" to="-715835444#1" type="bike_bicycle"/>
    <trip id="bike145" depart="623.78" from="378479743#1" to="-378479743#2" type="bike_bicycle"/>
    <trip id="bike146" depart="624.95" from="116556686#1" to="73372559" type="bike_bicycle"/>
    <trip id="bike147" depart="632.77" from="4195610#2" to="1290085525#0" type="bike_bicycle"/>
    <trip id="bike148" depart="633.10" from="378479743#4" to="715835444#1" type="bike_bicycle"/>
    <trip id="bike149" depart="634.67" from="-715835444#2" to="116556686#1" type="bike_bicycle"/>
    <trip id="bike150" depart="641.06" from="56163443#1" to="59591195#2" type="bike_bicycle"/>
    <trip id="bike151" depart="644.68" from="4144040#4" to="624481020#2" type="bike_bicycle"/>
    <trip id="bike152" depart="651.09" from="484022097" to="4144040#4" type="bike_bicycle"/>
    <trip id="bike153" depart="653.19" from="23248109#1" to="395456768" type="bike_bicycle"/>
    <trip id="bike154" depart="658.64" from="150041551#0" to="-881694399" type="bike_bicycle"/>
    <trip id="bike155" depart="661.02" from="1265069358#1" to="-4144040#2" type="bike_bicycle"/>
    <trip id="bike156" depart="661.03" from="-484022097" to="715835444#3" type="bike_bicycle"/>
    <trip id="bike157" depart="673.93" from="196656222#0" to="-4295817#3" type="bike_bicycle"/>
    <trip id="bike158" depart="676.44" from="-378479743#3" to="-182982119#1" type="bike_bicycle"/>
    <trip id="bike159" depart="679.37" from="689912267#0" to="-23248109#0" type="bike_bicycle"/>
    <trip id="bike160" depart="681.38" from="51873805" to="624481020#4" type="bike_bicycle"/>
    <trip id="bike161" depart="695.06" from="700440131" to="-150032770#5" type="bike_bicycle"/>
    <trip id="bike162" depart="696.29" from="103958941#0" to="506013711#1" type="bike_bicycle"/>
    <trip id="bike163" depart="725.60" from="-378479743#2" to="116556686#1" type="bike_bicycle"/>
    <trip id="bike164" depart="731.20" from="-4144040#2" to="624481020#2" type="bike_bicycle"/>
    <trip id="bike165" depart="744.48" from="51873805" to="59591195#1" type="bike_bicycle"/>
    <trip id="bike166" depart="751.29" from="-4144040#2" to="150032770#6" type="bike_bicycle"/>
    <trip id="bike167" depart="768.88" from="150032770#2" to="4144040#3" type="bike_bicycle"/>
    <trip id="bike168" depart="778.57" from="-624481020#1" to="150041551#0" type="bike_bicycle"/>
    <trip id="bike169" depart="778.97" from="-70205228#0" to="44973978" type="bike_bicycle"/>
    <trip id="bike170" depart="779.07" from="150041578" to="23248109#0" type="bike_bicycle"/>
    <trip id="bike171" depart="782.24" from="-715835444#2" to="59591195#1" type="bike_bicycle"/>
    <trip id="bike172" depart="784.27" from="150041593" to="624481020#4" type="bike_bicycle"/>
    <trip id="bike173" depart="784.88" from="1265069359" to="715835444#3" type="bike_bicycle"/>
    <trip id="bike174" depart="787.96" from="881694399" to="150041578" type="bike_bicycle"/>
    <trip id="bike175" depart="788.47" from="-700440136" to="116556688" type="bike_bicycle"/>
    <trip id="bike176" depart="807.64" from="23248109#1" to="715913363#2" type="bike_bicycle"/>
    <trip id="bike177" depart="810.24" from="624481020#0" to="59591195#0" type="bike_bicycle"/>
    <trip id="bike178" depart="812.09" from="-378479743#3" to="-56163443#3" type="bike_bicycle"/>
    <trip id="bike179" depart="814.61" from="4019053#2" to="700440130#0" type="bike_bicycle"/>
    <trip id="bike180" depart="815.58" from="24509268" to="-23248109#0" type="bike_bicycle"/>
    <trip id="bike181" depart="816.69" from="700236092#0" to="700236092#1" type="bike_bicycle"/>
    <trip id="bike182" depart="822.56" from="-70205228#0" to="492925920#1" type="bike_bicycle"/>
    <trip id="bike183" depart="833.29" from="-700440130#1" to="700440139" type="bike_bicycle"/>
    <trip id="bike184" depart="833.51" from="-378479743#5" to="150032770#6" type="bike_bicycle"/>
    <trip id="bike185" depart="836.85" from="715835444#3" to="-4295817#1" type="bike_bicycle"/>
    <trip id="bike186" depart="847.92" from="150041579#0" to="-715835444#4" type="bike_bicycle"/>
    <trip id="bike187" depart="858.06" from="-150032770#2" to="-150041551#1" type="bike_bicycle"/>
    <trip id="bike188" depart="860.17" from="214812786" to="-51873805" type="bike_bicycle"/>
    <trip id="bike189" depart="866.11" from="E2" to="116556686#1" type="bike_bicycle"/>
    <trip id="bike190" depart="867.93" from="-150032770#5" to="70205228#2" type="bike_bicycle"/>
    <trip id="bike191" depart="868.60" from="689912267#0" to="395456769#0" type="bike_bicycle"/>
    <trip id="bike192" depart="870.57" from="56163443#1" to="-378479743#1" type="bike_bicycle"/>
    <trip id="bike193" depart="873.46" from="-70205228#0" to="624481020#2" type="bike_bicycle"/>
    <trip id="bike194" depart="875.69" from="4195610#2" to="-378479743#1" type="bike_bicycle"/>
    <trip id="bike195" depart="877.93" from="4295817#0" to="150041551#1" type="bike_bicycle"/>
    <trip id="bike196" depart="881.71" from="-1265069358#1" to="-196656222#0" type="bike_bicycle"/>
    <trip id="bike197" depart="889.22" from="-700440128" to="624481020#4" type="bike_bicycle"/>
    <trip id="bike198" depart="896.61" from="23508224" to="4295817#3" type="bike_bicycle"/>
    <trip id="bike199" depart="897.38" from="23248109#1" to="-23248109#1" type="bike_bicycle"/>
    <trip id="bike200" depart="898.22" from="-70205228#0" to="-700440130#0" type="bike_bicycle"/>
    <trip id="bike201" depart="899.34" from="-150041551#1" to="150032770#1" type="bike_bicycle"/>
    <trip id="bike202" depart="906.17" from="56163443#1" to="150041551#2" type="bike_bicycle"/>
    <trip id="bike203" depart="911.93" from="-23508141#1" to="700440139" type="bike_bicycle"/>
    <trip id="bike204" depart="913.21" from="378479743#4" to="-1290085526#1" type="bike_bicycle"/>
    <trip id="bike205" depart="914.75" from="23015831" to="-53207957" type="bike_bicycle"/>
    <trip id="bike206" depart="920.17" from="-378479743#4" to="150032770#2" type="bike_bicycle"/>
    <trip id="bike207" depart="920.65" from="378479753" to="-53207957" type="bike_bicycle"/>
    <trip id="bike208" depart="937.77" from="150032770#5" to="4019053#2" type="bike_bicycle"/>
    <trip id="bike209" depart="942.51" from="-23015831" to="75392301#0" type="bike_bicycle"/>
    <trip id="bike210" depart="947.83" from="-196656222#0" to="23015831" type="bike_bicycle"/>
    <trip id="bike211" depart="951.88" from="214812788#2" to="881694399" type="bike_bicycle"/>
    <trip id="bike212" depart="952.14" from="24509268" to="1265069358#1" type="bike_bicycle"/>
    <trip id="bike213" depart="953.61" from="150041593" to="378479753" type="bike_bicycle"/>
    <trip id="bike214" depart="956.03" from="75392301#1" to="-60263960" type="bike_bicycle"/>
    <trip id="bike215" depart="956.23" from="-150032770#0" to="53207959#3" type="bike_bicycle"/>
    <trip id="bike216" depart="960.31" from="116556686#1" to="43135644#0" type="bike_bicycle"/>
    <trip id="bike217" depart="961.18" from="395456769#0" to="506015829#1" type="bike_bicycle"/>
    <trip id="bike218" depart="962.13" from="484022097" to="-715835444#1" type="bike_bicycle"/>
    <trip id="bike219" depart="968.46" from="-150041551#0" to="23508141#0" type="bike_bicycle"/>
    <trip id="bike220" depart="974.29" from="60263960" to="-4144040#1" type="bike_bicycle"/>
    <trip id="bike221" depart="977.65" from="53207959#1" to="150041579#0" type="bike_bicycle"/>
    <trip id="bike222" depart="979.59" from="4195610#2" to="378479753" type="bike_bicycle"/>
    <trip id="bike223" depart="982.65" from="60263960" to="-150041565" type="bike_bicycle"/>
    <trip id="bike224" depart="984.89" from="53207959#0" to="150041551#2" type="bike_bicycle"/>
    <trip id="bike225" depart="986.84" from="-70205228#1" to="-150032770#6" type="bike_bicycle"/>
    <trip id="bike226" depart="988.77" from="-4295817#0" to="-150032770#6" type="bike_bicycle"/>
    <trip id="bike227" depart="994.37" from="715835444#1" to="214812786" type="bike_bicycle"/>
    <trip id="bike228" depart="996.42" from="E0" to="23508141#0" type="bike_bicycle"/>
    <trip id="bike229" depart="998.96" from="-689912267#0" to="484022097" type="bike_bicycle"/>
    <trip id="bike230" depart="998.96" from="-4195580#2" to="-715835444#5" type="bike_bicycle"/>
    <trip id="bike231" depart="1000.98" from="53207959#1" to="700440128" type="bike_bicycle"/>
    <trip id="bike232" depart="1002.18" from="-881694399" to="-23508224" type="bike_bicycle"/>
    <trip id="bike233" depart="1015.89" from="1265069359" to="700440134" type="bike_bicycle"/>
    <trip id="bike234" depart="1016.60" from="492925919" to="700440137" type="bike_bicycle"/>
    <trip id="bike235" depart="1020.63" from="1290085526#0" to="75392301#0" type="bike_bicycle"/>
    <trip id="bike236" depart="1022.57" from="196656222#2" to="196656222#0" type="bike_bicycle"/>
    <trip id="bike237" depart="1024.07" from="70205228#1" to="214812786" type="bike_bicycle"/>
    <trip id="bike238" depart="1026.36" from="59591195#1" to="4295817#3" type="bike_bicycle"/>
    <trip id="bike239" depart="1029.10" from="-196656222#2" to="378479743#1" type="bike_bicycle"/>
    <trip id="bike240" depart="1029.44" from="624481020#1" to="23508141#0" type="bike_bicycle"/>
    <trip id="bike241" depart="1033.78" from="-715835444#4" to="-196656222#0" type="bike_bicycle"/>
    <trip id="bike242" depart="1049.20" from="4144040#2" to="-700440130#1" type="bike_bicycle"/>
    <trip id="bike243" depart="1069.78" from="378479743#5" to="150032770#2" type="bike_bicycle"/>
    <trip id="bike244" depart="1081.24" from="4195610#0" to="-715835444#4" type="bike_bicycle"/>
    <trip id="bike245" depart="1083.22" from="-150041551#0" to="700440129" type="bike_bicycle"/>
    <trip id="bike246" depart="1083.81" from="116556688" to="E2" type="bike_bicycle"/>
    <trip id="bike247" depart="1086.67" from="-700440130#1" to="75392301#1" type="bike_bicycle"/>
    <trip id="bike248" depart="1092.37" from="715835444#3" to="-182982119#1" type="bike_bicycle"/>
    <trip id="bike249" depart="1092.94" from="395456769#1" to="103958941#0" type="bike_bicycle"/>
    <trip id="bike250" depart="1093.79" from="59591195#1" to="4144040#3" type="bike_bicycle"/>
    <trip id="bike251" depart="1094.50" from="715835444#4" to="-378479743#2" type="bike_bicycle"/>
    <trip id="bike252" depart="1099.45" from="378479743#6" to="53207959#0" type="bike_bicycle"/>
    <trip id="bike253" depart="1103.10" from="-150032770#6" to="-150041594#1" type="bike_bicycle"/>
    <trip id="bike254" depart="1105.87" from="53207959#1" to="103958941#0" type="bike_bicycle"/>
    <trip id="bike255" depart="1109.53" from="1290085525#1" to="23508224" type="bike_bicycle"/>
    <trip id="bike256" depart="1115.78" from="378479743#5" to="4144040#3" type="bike_bicycle"/>
    <trip id="bike257" depart="1116.86" from="715835444#3" to="103958941#2" type="bike_bicycle"/>
    <trip id="bike258" depart="1117.92" from="506015829#1" to="24509268" type="bike_bicycle"/>
    <trip id="bike259" depart="1126.72" from="23508141#0" to="1290085525#1" type="bike_bicycle"/>
    <trip id="bike260" depart="1131.16" from="4144040#0" to="-56163443#3" type="bike_bicycle"/>
    <trip id="bike261" depart="1131.64" from="-23508224" to="43135644#0" type="bike_bicycle"/>
    <trip id="bike262" depart="1132.68" from="196656222#2" to="1265069358#1" type="bike_bicycle"/>
    <trip id="bike263" depart="1133.15" from="35574708#1" to="-624481020#0" type="bike_bicycle"/>
    <trip id="bike264" depart="1135.66" from="-700440128" to="150041551#0" type="bike_bicycle"/>
    <trip id="bike265" depart="1138.58" from="E2" to="-700440128" type="bike_bicycle"/>
    <trip id="bike266" depart="1138.67" from="700440148" to="150041594#0" type="bike_bicycle"/>
    <trip id="bike267" depart="1139.05" from="-378479743#1" to="700236092#1" type="bike_bicycle"/>
    <trip id="bike268" depart="1139.71" from="150041579#0" to="700440137" type="bike_bicycle"/>
    <trip id="bike269" depart="1139.71" from="150041578" to="-196656222#1" type="bike_bicycle"/>
    <trip id="bike270" depart="1141.65" from="4195580#1" to="700236092#0" type="bike_bicycle"/>
    <trip id="bike271" depart="1142.41" from="-715835444#4" to="-715835444#4" type="bike_bicycle"/>
    <trip id="bike272" depart="1143.00" from="-182982119#1" to="23508141#0" type="bike_bicycle"/>
    <trip id="bike273" depart="1145.26" from="700440134" to="700236092#1" type="bike_bicycle"/>
    <trip id="bike274" depart="1158.32" from="4295817#3" to="70205228#1" type="bike_bicycle"/>
    <trip id="bike275" depart="1159.73" from="395456769#1" to="56163443#1" type="bike_bicycle"/>
    <trip id="bike276" depart="1164.50" from="214812788#2" to="-23508141#1" type="bike_bicycle"/>
    <trip id="bike277" depart="1167.73" from="-4295817#1" to="-378479743#1" type="bike_bicycle"/>
    <trip id="bike278" depart="1175.50" from="56163443#1" to="-150032770#1" type="bike_bicycle"/>
    <trip id="bike279" depart="1177.06" from="24509268" to="103958941#2" type="bike_bicycle"/>
    <trip id="bike280" depart="1178.25" from="59591195#1" to="23508141#1" type="bike_bicycle"/>
    <trip id="bike281" depart="1179.88" from="378479753" to="-196656222#1" type="bike_bicycle"/>
    <trip id="bike282" depart="1180.02" from="-715835444#2" to="E2" type="bike_bicycle"/>
    <trip id="bike283" depart="1195.73" from="43135644#0" to="23015831" type="bike_bicycle"/>
    <trip id="bike284" depart="1201.19" from="51873805" to="624481020#1" type="bike_bicycle"/>
    <trip id="bike285" depart="1205.50" from="-196656222#1" to="75392301#0" type="bike_bicycle"/>
    <trip id="bike286" depart="1209.47" from="4019053#2" to="150041551#1" type="bike_bicycle"/>
    <trip id="bike287" depart="1211.52" from="4195580#1" to="-715835444#3" type="bike_bicycle"/>
    <trip id="bike288" depart="1211.72" from="700440130#1" to="53207959#0" type="bike_bicycle"/>
    <trip id="bike289" depart="1213.06" from="4019053#2" to="-4144040#2" type="bike_bicycle"/>
    <trip id="bike290" depart="1215.80" from="715913363#2" to="150032770#5" type="bike_bicycle"/>
    <trip id="bike291" depart="1225.44" from="700440139" to="-150041551#1" type="bike_bicycle"/>
    <trip id="bike292" depart="1226.55" from="-378479743#1" to="-378479743#4" type="bike_bicycle"/>
    <trip id="bike293" depart="1228.18" from="-4144040#2" to="-70205228#1" type="bike_bicycle"/>
    <trip id="bike294" depart="1230.99" from="4295817#1" to="-715835444#3" type="bike_bicycle"/>
    <trip id="bike295" depart="1232.94" from="715835444#2" to="700440137" type="bike_bicycle"/>
    <trip id="bike296" depart="1235.48" from="700236092#0" to="-56163443#3" type="bike_bicycle"/>
    <trip id="bike297" depart="1238.06" from="395456769#1" to="23508141#1" type="bike_bicycle"/>
    <trip id="bike298" depart="1239.53" from="-378479743#1" to="-700440130#1" type="bike_bicycle"/>
    <trip id="bike299" depart="1244.03" from="23508141#1" to="196656222#0" type="bike_bicycle"/>
    <trip id="bike300" depart="1245.94" from="-4144040#3" to="715835444#2" type="bike_bicycle"/>
    <trip id="bike301" depart="1246.61" from="-378479743#6" to="395456769#1" type="bike_bicycle"/>
    <trip id="bike302" depart="1259.27" from="43135644#0" to="378479743#2" type="bike_bicycle"/>
    <trip id="bike303" depart="1259.29" from="689912267#0" to="23508142#1" type="bike_bicycle"/>
    <trip id="bike304" depart="1262.85" from="624481020#1" to="-150032770#2" type="bike_bicycle"/>
    <trip id="bike305" depart="1265.67" from="-150041551#1" to="38115188" type="bike_bicycle"/>
    <trip id="bike306" depart="1266.57" from="378479743#0" to="395456769#0" type="bike_bicycle"/>
    <trip id="bike307" depart="1271.89" from="51873805" to="150032770#0" type="bike_bicycle"/>
    <trip id="bike308" depart="1272.03" from="4019053#2" to="196656222#0" type="bike_bicycle"/>
    <trip id="bike309" depart="1274.03" from="395456768" to="-700440128" type="bike_bicycle"/>
    <trip id="bike310" depart="1277.89" from="715835444#5" to="150041593" type="bike_bicycle"/>
    <trip id="bike311" depart="1284.90" from="59591195#1" to="4144040#4" type="bike_bicycle"/>
    <trip id="bike312" depart="1288.91" from="-70205228#2" to="-182982119#1" type="bike_bicycle"/>
    <trip id="bike313" depart="1295.60" from="-150041594#1" to="150032770#6" type="bike_bicycle"/>
    <trip id="bike314" depart="1295.63" from="196656222#0" to="-4195580#1" type="bike_bicycle"/>
    <trip id="bike315" depart="1315.96" from="378479743#6" to="-700440136" type="bike_bicycle"/>
    <trip id="bike316" depart="1324.43" from="43135644#0" to="43135644#0" type="bike_bicycle"/>
    <trip id="bike317" depart="1327.90" from="700236093" to="75392301#0" type="bike_bicycle"/>
    <trip id="bike318" depart="1328.29" from="-378479743#2" to="103958941#2" type="bike_bicycle"/>
    <trip id="bike319" depart="1338.04" from="35574708#1" to="-70205228#1" type="bike_bicycle"/>
    <trip id="bike320" depart="1338.68" from="150041580" to="-624481020#1" type="bike_bicycle"/>
    <trip id="bike321" depart="1343.78" from="-624481020#4" to="-23015831" type="bike_bicycle"/>
    <trip id="bike322" depart="1354.32" from="-70205228#1" to="116556688" type="bike_bicycle"/>
    <trip id="bike323" depart="1356.02" from="378479753" to="-56163443#3" type="bike_bicycle"/>
    <trip id="bike324" depart="1359.99" from="700440128" to="-378479743#5" type="bike_bicycle"/>
    <trip id="bike325" depart="1372.64" from="-715835444#5" to="254075881#1" type="bike_bicycle"/>
    <trip id="bike326" depart="1375.28" from="-715835444#3" to="492925920#1" type="bike_bicycle"/>
    <trip id="bike327" depart="1378.47" from="196656222#2" to="214812786" type="bike_bicycle"/>
    <trip id="bike328" depart="1386.53" from="196656222#2" to="-700440136" type="bike_bicycle"/>
    <trip id="bike329" depart="1387.48" from="-150032770#2" to="715835444#3" type="bike_bicycle"/>
    <trip id="bike330" depart="1394.83" from="214812786" to="73372559" type="bike_bicycle"/>
    <trip id="bike331" depart="1395.33" from="-484022097" to="-715835444#5" type="bike_bicycle"/>
    <trip id="bike332" depart="1397.43" from="-150041551#3" to="182982119#0" type="bike_bicycle"/>
    <trip id="bike333" depart="1408.35" from="700440130#1" to="395456769#1" type="bike_bicycle"/>
    <trip id="bike334" depart="1413.81" from="150041593" to="23248109#1" type="bike_bicycle"/>
    <trip id="bike335" depart="1415.49" from="700236092#0" to="150032770#5" type="bike_bicycle"/>
    <trip id="bike336" depart="1415.99" from="700440130#1" to="4295817#3" type="bike_bicycle"/>
    <trip id="bike337" depart="1422.16" from="506015829#1" to="103958941#0" type="bike_bicycle"/>
    <trip id="bike338" depart="1429.90" from="150032770#1" to="24509268" type="bike_bicycle"/>
    <trip id="bike339" depart="1433.00" from="-4295817#0" to="23508142#0" type="bike_bicycle"/>
    <trip id="bike340" depart="1433.67" from="-196656222#1" to="196656222#1" type="bike_bicycle"/>
    <trip id="bike341" depart="1440.12" from="506015829#1" to="-689912267#0" type="bike_bicycle"/>
    <trip id="bike342" depart="1470.46" from="E0" to="4144040#3" type="bike_bicycle"/>
    <trip id="bike343" depart="1478.10" from="-378479743#0" to="75392301#0" type="bike_bicycle"/>
    <trip id="bike344" depart="1481.32" from="149518769#1" to="56163443#1" type="bike_bicycle"/>
    <trip id="bike345" depart="1481.53" from="103958941#2" to="715835444#2" type="bike_bicycle"/>
    <trip id="bike346" depart="1483.95" from="492925920#1" to="-4195580#0" type="bike_bicycle"/>
    <trip id="bike347" depart="1486.93" from="214812788#2" to="196656222#0" type="bike_bicycle"/>
    <trip id="bike348" depart="1494.86" from="-150041551#1" to="-378479743#1" type="bike_bicycle"/>
    <trip id="bike349" depart="1498.26" from="-881694399" to="150041579#2" type="bike_bicycle"/>
    <trip id="bike350" depart="1510.10" from="150041579#2" to="378479743#2" type="bike_bicycle"/>
    <trip id="bike351" depart="1511.20" from="23015831" to="-70205228#2" type="bike_bicycle"/>
    <trip id="bike352" depart="1516.81" from="378479753" to="-378479743#6" type="bike_bicycle"/>
    <trip id="bike353" depart="1517.00" from="E0" to="449551311" type="bike_bicycle"/>
    <trip id="bike354" depart="1521.13" from="-70205228#2" to="-715835444#2" type="bike_bicycle"/>
    <trip id="bike355" depart="1531.28" from="624481020#2" to="23248109#0" type="bike_bicycle"/>
    <trip id="bike356" depart="1535.69" from="4295817#1" to="-700440130#0" type="bike_bicycle"/>
    <trip id="bike357" depart="1550.26" from="60263960" to="103958941#0" type="bike_bicycle"/>
    <trip id="bike358" depart="1552.15" from="4195580#0" to="75392301#1" type="bike_bicycle"/>
    <trip id="bike359" depart="1552.51" from="378479743#2" to="56163443#1" type="bike_bicycle"/>
    <trip id="bike360" depart="1552.57" from="449551311" to="4195580#0" type="bike_bicycle"/>
    <trip id="bike361" depart="1552.85" from="-150032770#2" to="150041579#2" type="bike_bicycle"/>
    <trip id="bike362" depart="1557.00" from="73372559" to="53207959#1" type="bike_bicycle"/>
    <trip id="bike363" depart="1558.30" from="53207959#0" to="254075881#1" type="bike_bicycle"/>
    <trip id="bike364" depart="1561.22" from="43135644#0" to="35574708#1" type="bike_bicycle"/>
    <trip id="bike365" depart="1562.18" from="-4144040#3" to="378479743#6" type="bike_bicycle"/>
    <trip id="bike366" depart="1563.61" from="38115188" to="689912267#0" type="bike_bicycle"/>
    <trip id="bike367" depart="1571.99" from="-378479743#5" to="4144040#3" type="bike_bicycle"/>
    <trip id="bike368" depart="1572.35" from="-150032770#5" to="715835444#3" type="bike_bicycle"/>
    <trip id="bike369" depart="1577.21" from="-23508141#1" to="-150032770#0" type="bike_bicycle"/>
    <trip id="bike370" depart="1592.40" from="-715835444#3" to="-378479743#4" type="bike_bicycle"/>
    <trip id="bike371" depart="1599.55" from="4195610#0" to="149518769#1" type="bike_bicycle"/>
    <trip id="bike372" depart="1613.91" from="53207959#0" to="70205228#0" type="bike_bicycle"/>
    <trip id="bike373" depart="1621.03" from="700440130#0" to="43135644#0" type="bike_bicycle"/>
    <trip id="bike374" depart="1621.59" from="-182982119#1" to="-378479743#1" type="bike_bicycle"/>
    <trip id="bike375" depart="1624.53" from="-4295817#3" to="-70205228#2" type="bike_bicycle"/>
    <trip id="bike376" depart="1627.56" from="4144040#3" to="23015831" type="bike_bicycle"/>
    <trip id="bike377" depart="1633.00" from="-715835444#3" to="-4144040#0" type="bike_bicycle"/>
    <trip id="bike378" depart="1634.70" from="700440148" to="-715835444#3" type="bike_bicycle"/>
    <trip id="bike379" depart="1635.68" from="116556688" to="506015829#1" type="bike_bicycle"/>
    <trip id="bike380" depart="1636.29" from="43135644#0" to="395456768" type="bike_bicycle"/>
    <trip id="bike381" depart="1637.11" from="4195610#0" to="378479743#3" type="bike_bicycle"/>
    <trip id="bike382" depart="1643.61" from="-4195580#2" to="-56163443#3" type="bike_bicycle"/>
    <trip id="bike383" depart="1648.63" from="254075881#1" to="-4295817#3" type="bike_bicycle"/>
    <trip id="bike384" depart="1648.77" from="75392301#0" to="-700440130#0" type="bike_bicycle"/>
    <trip id="bike385" depart="1653.24" from="-70205228#1" to="-4195580#2" type="bike_bicycle"/>
    <trip id="bike386" depart="1656.43" from="4295817#0" to="-70205228#0" type="bike_bicycle"/>
    <trip id="bike387" depart="1664.63" from="116556686#1" to="715835444#1" type="bike_bicycle"/>
    <trip id="bike388" depart="1664.90" from="59591195#0" to="-624481020#3" type="bike_bicycle"/>
    <trip id="bike389" depart="1669.17" from="-378479743#0" to="4144040#3" type="bike_bicycle"/>
    <trip id="bike390" depart="1671.54" from="1290085525#1" to="75392301#1" type="bike_bicycle"/>
    <trip id="bike391" depart="1672.15" from="624481020#0" to="715835444#4" type="bike_bicycle"/>
    <trip id="bike392" depart="1672.23" from="59591195#1" to="-700440128" type="bike_bicycle"/>
    <trip id="bike393" depart="1673.30" from="-70205228#0" to="4195610#2" type="bike_bicycle"/>
    <trip id="bike394" depart="1679.52" from="116556686#1" to="150041551#0" type="bike_bicycle"/>
    <trip id="bike395" depart="1686.28" from="-700440128" to="150041580" type="bike_bicycle"/>
    <trip id="bike396" depart="1692.62" from="-4295817#1" to="23248109#1" type="bike_bicycle"/>
    <trip id="bike397" depart="1697.40" from="70205228#2" to="4195580#1" type="bike_bicycle"/>
    <trip id="bike398" depart="1699.11" from="-378479743#3" to="378479743#4" type="bike_bicycle"/>
    <trip id="bike399" depart="1701.50" from="378479743#2" to="-53207957" type="bike_bicycle"/>
    <trip id="bike400" depart="1701.78" from="4144040#4" to="23248109#0" type="bike_bicycle"/>
    <trip id="bike401" depart="1703.13" from="395456769#1" to="-150041551#1" type="bike_bicycle"/>
    <trip id="bike402" depart="1704.19" from="150032770#5" to="4295817#0" type="bike_bicycle"/>
    <trip id="bike403" depart="1716.50" from="-23508141#0" to="506013711#1" type="bike_bicycle"/>
    <trip id="bike404" depart="1716.89" from="-1265069358#1" to="23508141#1" type="bike_bicycle"/>
    <trip id="bike405" depart="1718.97" from="70205228#2" to="1290085526#0" type="bike_bicycle"/>
    <trip id="bike406" depart="1720.71" from="715835444#1" to="700440130#1" type="bike_bicycle"/>
    <trip id="bike407" depart="1722.72" from="150041594#0" to="-4195580#0" type="bike_bicycle"/>
    <trip id="bike408" depart="1729.82" from="715913363#2" to="-70205228#1" type="bike_bicycle"/>
    <trip id="bike409" depart="1731.21" from="4144040#0" to="700440139" type="bike_bicycle"/>
    <trip id="bike410" depart="1732.55" from="-23248109#0" to="24509268" type="bike_bicycle"/>
    <trip id="bike411" depart="1734.07" from="23508141#1" to="4295817#1" type="bike_bicycle"/>
    <trip id="bike412" depart="1734.43" from="715835444#1" to="700440148" type="bike_bicycle"/>
    <trip id="bike413" depart="1737.79" from="-4144040#4" to="700440130#1" type="bike_bicycle"/>
    <trip id="bike414" depart="1747.97" from="-4144040#4" to="70205228#0" type="bike_bicycle"/>
    <trip id="bike415" depart="1754.23" from="E2" to="1290085525#1" type="bike_bicycle"/>
    <trip id="bike416" depart="1754.29" from="196656222#2" to="715835444#1" type="bike_bicycle"/>
    <trip id="bike417" depart="1757.00" from="715913363#2" to="70205228#1" type="bike_bicycle"/>
    <trip id="bike418" depart="1760.39" from="700440130#0" to="-1265069360#0" type="bike_bicycle"/>
    <trip id="bike419" depart="1765.38" from="378479740#1" to="-23248109#1" type="bike_bicycle"/>
    <trip id="bike420" depart="1766.43" from="75392301#1" to="-689912267#0" type="bike_bicycle"/>
    <trip id="bike421" depart="1777.88" from="E0" to="23508141#0" type="bike_bicycle"/>
    <trip id="bike422" depart="1780.84" from="196656222#1" to="715835444#2" type="bike_bicycle"/>
    <trip id="bike423" depart="1783.71" from="700236092#1" to="150041579#0" type="bike_bicycle"/>
    <trip id="bike424" depart="1784.84" from="-4195580#2" to="-23508141#0" type="bike_bicycle"/>
    <trip id="bike425" depart="1786.64" from="-4144040#2" to="150041578" type="bike_bicycle"/>
    <trip id="bike426" depart="1787.19" from="-700440128" to="-4144040#3" type="bike_bicycle"/>
    <trip id="bike427" depart="1794.35" from="484022097" to="53207959#3" type="bike_bicycle"/>
    <trip id="bike428" depart="1794.46" from="378479740#1" to="492925919" type="bike_bicycle"/>
    <trip id="bike429" depart="1798.16" from="-4144040#4" to="700236093" type="bike_bicycle"/>
    <trip id="bike430" depart="1801.73" from="700440137" to="624481020#2" type="bike_bicycle"/>
    <trip id="bike431" depart="1805.47" from="23015831" to="-196656222#1" type="bike_bicycle"/>
    <trip id="bike432" depart="1809.35" from="4144040#4" to="-4144040#3" type="bike_bicycle"/>
    <trip id="bike433" depart="1811.40" from="-378479743#4" to="-70205228#1" type="bike_bicycle"/>
    <trip id="bike434" depart="1813.49" from="-624481020#4" to="-624481020#0" type="bike_bicycle"/>
    <trip id="bike435" depart="1815.07" from="-624481020#1" to="484022097" type="bike_bicycle"/>
    <trip id="bike436" depart="1821.89" from="715835444#4" to="-700440130#1" type="bike_bicycle"/>
    <trip id="bike437" depart="1835.47" from="449551311" to="-1290085526#1" type="bike_bicycle"/>
    <trip id="bike438" depart="1839.74" from="4144040#1" to="4195580#1" type="bike_bicycle"/>
    <trip id="bike439" depart="1843.89" from="-182982119#1" to="-23508141#1" type="bike_bicycle"/>
    <trip id="bike440" depart="1849.67" from="-715835444#2" to="1290085526#0" type="bike_bicycle"/>
    <trip id="bike441" depart="1858.38" from="214812786" to="700440137" type="bike_bicycle"/>
    <trip id="bike442" depart="1858.62" from="4295817#0" to="-700440136" type="bike_bicycle"/>
    <trip id="bike443" depart="1862.30" from="-378479743#0" to="700440148" type="bike_bicycle"/>
    <trip id="bike444" depart="1862.55" from="-70205228#2" to="378479743#4" type="bike_bicycle"/>
    <trip id="bike445" depart="1863.27" from="-53207957" to="-378479743#0" type="bike_bicycle"/>
    <trip id="bike446" depart="1865.23" from="-378479743#6" to="44973978" type="bike_bicycle"/>
    <trip id="bike447" depart="1871.60" from="378479743#6" to="150032770#0" type="bike_bicycle"/>
    <trip id="bike448" depart="1877.68" from="23508224" to="150041579#2" type="bike_bicycle"/>
    <trip id="bike449" depart="1882.19" from="23508141#1" to="4019053#2" type="bike_bicycle"/>
    <trip id="bike450" depart="1891.16" from="-53207957" to="-56163443#3" type="bike_bicycle"/>
    <trip id="bike451" depart="1893.34" from="492925920#1" to="700440130#0" type="bike_bicycle"/>
    <trip id="bike452" depart="1894.85" from="-196656222#2" to="150041551#0" type="bike_bicycle"/>
    <trip id="bike453" depart="1903.33" from="4295817#0" to="-182982119#1" type="bike_bicycle"/>
    <trip id="bike454" depart="1903.89" from="35574708#1" to="-150041565" type="bike_bicycle"/>
    <trip id="bike455" depart="1904.47" from="23508224" to="196656222#1" type="bike_bicycle"/>
    <trip id="bike456" depart="1904.83" from="378479743#0" to="-378479743#3" type="bike_bicycle"/>
    <trip id="bike457" depart="1912.44" from="-881694399" to="214812788#2" type="bike_bicycle"/>
    <trip id="bike458" depart="1917.56" from="-23508224" to="-4195580#1" type="bike_bicycle"/>
    <trip id="bike459" depart="1919.04" from="378479743#1" to="-196656222#2" type="bike_bicycle"/>
    <trip id="bike460" depart="1924.83" from="214812788#2" to="59591195#1" type="bike_bicycle"/>
    <trip id="bike461" depart="1925.62" from="150041579#0" to="196656222#2" type="bike_bicycle"/>
    <trip id="bike462" depart="1927.10" from="150041579#2" to="-150041551#3" type="bike_bicycle"/>
    <trip id="bike463" depart="1931.85" from="150041580" to="59591195#1" type="bike_bicycle"/>
    <trip id="bike464" depart="1936.87" from="449551311" to="1290085525#0" type="bike_bicycle"/>
    <trip id="bike465" depart="1938.90" from="60263960" to="44973978" type="bike_bicycle"/>
    <trip id="bike466" depart="1946.31" from="378479743#1" to="-150041551#0" type="bike_bicycle"/>
    <trip id="bike467" depart="1946.50" from="116556686#1" to="-150041565" type="bike_bicycle"/>
    <trip id="bike468" depart="1950.42" from="E0" to="715835444#1" type="bike_bicycle"/>
    <trip id="bike469" depart="1952.07" from="-196656222#0" to="715835444#1" type="bike_bicycle"/>
    <trip id="bike470" depart="1953.55" from="-150032770#5" to="149518769#1" type="bike_bicycle"/>
    <trip id="bike471" depart="1960.94" from="51873805" to="506013711#1" type="bike_bicycle"/>
    <trip id="bike472" depart="1971.10" from="75392301#1" to="395456768" type="bike_bicycle"/>
    <trip id="bike473" depart="1976.77" from="150032770#6" to="E0" type="bike_bicycle"/>
    <trip id="bike474" depart="1980.58" from="1290085525#1" to="700440129" type="bike_bicycle"/>
    <trip id="bike475" depart="1984.12" from="700440139" to="116556686#1" type="bike_bicycle"/>
    <trip id="bike476" depart="1989.55" from="4195580#1" to="4019053#2" type="bike_bicycle"/>
    <trip id="bike477" depart="1999.55" from="23508142#0" to="395456769#0" type="bike_bicycle"/>
    <trip id="bike478" depart="2001.38" from="116556686#1" to="-4144040#1" type="bike_bicycle"/>
    <trip id="bike479" depart="2005.08" from="23508141#1" to="23015831" type="bike_bicycle"/>
    <trip id="bike480" depart="2014.24" from="44973978" to="-4295817#1" type="bike_bicycle"/>
    <trip id="bike481" depart="2014.69" from="-1265069358#1" to="-150032770#1" type="bike_bicycle"/>
    <trip id="bike482" depart="2022.77" from="-70205228#2" to="4144040#2" type="bike_bicycle"/>
    <trip id="bike483" depart="2029.55" from="23508224" to="23248109#0" type="bike_bicycle"/>
    <trip id="bike484" depart="2041.28" from="624481020#1" to="-56163443#3" type="bike_bicycle"/>
    <trip id="bike485" depart="2044.36" from="116556686#1" to="-624481020#4" type="bike_bicycle"/>
    <trip id="bike486" depart="2049.25" from="715835444#1" to="4295817#1" type="bike_bicycle"/>
    <trip id="bike487" depart="2050.96" from="-23508224" to="59591195#1" type="bike_bicycle"/>
    <trip id="bike488" depart="2057.16" from="150032770#6" to="506013711#1" type="bike_bicycle"/>
    <trip id="bike489" depart="2072.17" from="700440131" to="-1290085526#1" type="bike_bicycle"/>
    <trip id="bike490" depart="2079.36" from="-4295817#3" to="-23248109#0" type="bike_bicycle"/>
    <trip id="bike491" depart="2080.90" from="-150032770#6" to="378479743#1" type="bike_bicycle"/>
    <trip id="bike492" depart="2087.03" from="4295817#0" to="-150041551#0" type="bike_bicycle"/>
    <trip id="bike493" depart="2094.33" from="492925919" to="1290085526#0" type="bike_bicycle"/>
    <trip id="bike494" depart="2111.30" from="-624481020#1" to="-4295817#0" type="bike_bicycle"/>
    <trip id="bike495" depart="2121.37" from="700440128" to="-150041551#3" type="bike_bicycle"/>
    <trip id="bike496" depart="2129.43" from="214812786" to="-700440128" type="bike_bicycle"/>
    <trip id="bike497" depart="2148.04" from="60263960" to="4295817#3" type="bike_bicycle"/>
    <trip id="bike498" depart="2161.16" from="-715835444#4" to="378479743#1" type="bike_bicycle"/>
    <trip id="bike499" depart="2166.40" from="4195580#0" to="-70205228#1" type="bike_bicycle"/>
    <trip id="bike500" depart="2174.65" from="-715835444#1" to="-378479743#2" type="bike_bicycle"/>
    <trip id="bike501" depart="2175.49" from="4144040#2" to="-4295817#1" type="bike_bicycle"/>
    <trip id="bike502" depart="2175.55" from="-715835444#1" to="-150041551#3" type="bike_bicycle"/>
    <trip id="bike503" depart="2187.70" from="715835444#3" to="700440130#1" type="bike_bicycle"/>
    <trip id="bike504" depart="2187.70" from="700440148" to="378479743#6" type="bike_bicycle"/>
    <trip id="bike505" depart="2194.07" from="150041551#0" to="182982119#0" type="bike_bicycle"/>
    <trip id="bike506" depart="2196.37" from="75392301#0" to="715835444#2" type="bike_bicycle"/>
    <trip id="bike507" depart="2196.45" from="4144040#4" to="53207959#1" type="bike_bicycle"/>
    <trip id="bike508" depart="2197.84" from="-715835444#4" to="150032770#0" type="bike_bicycle"/>
    <trip id="bike509" depart="2199.17" from="-378479743#5" to="116556686#1" type="bike_bicycle"/>
    <trip id="bike510" depart="2204.49" from="492925920#1" to="150041579#2" type="bike_bicycle"/>
    <trip id="bike511" depart="2205.30" from="700236092#0" to="-700440130#0" type="bike_bicycle"/>
    <trip id="bike512" depart="2206.99" from="4295817#1" to="59591195#1" type="bike_bicycle"/>
    <trip id="bike513" depart="2207.48" from="700440148" to="23508142#1" type="bike_bicycle"/>
    <trip id="bike514" depart="2209.66" from="73372559" to="23508142#0" type="bike_bicycle"/>
    <trip id="bike515" depart="2212.11" from="-378479743#3" to="-53207957" type="bike_bicycle"/>
    <trip id="bike516" depart="2214.31" from="-4295817#1" to="395456768" type="bike_bicycle"/>
    <trip id="bike517" depart="2222.01" from="70205228#1" to="700236092#0" type="bike_bicycle"/>
    <trip id="bike518" depart="2222.31" from="-23248109#0" to="4295817#1" type="bike_bicycle"/>
    <trip id="bike519" depart="2225.39" from="-4195580#2" to="-624481020#3" type="bike_bicycle"/>
    <trip id="bike520" depart="2225.53" from="4195580#0" to="378479743#1" type="bike_bicycle"/>
    <trip id="bike521" depart="2233.88" from="700440130#0" to="-4144040#3" type="bike_bicycle"/>
    <trip id="bike522" depart="2234.64" from="506015829#1" to="4295817#1" type="bike_bicycle"/>
    <trip id="bike523" depart="2236.56" from="254075881#1" to="150041580" type="bike_bicycle"/>
    <trip id="bike524" depart="2238.84" from="700440129" to="-715835444#1" type="bike_bicycle"/>
    <trip id="bike525" depart="2244.24" from="715835444#5" to="-1290085526#1" type="bike_bicycle"/>
    <trip id="bike526" depart="2244.28" from="715835444#1" to="715913363#2" type="bike_bicycle"/>
    <trip id="bike527" depart="2249.03" from="-378479743#0" to="E2" type="bike_bicycle"/>
    <trip id="bike528" depart="2253.96" from="182982119#0" to="-53207957" type="bike_bicycle"/>
    <trip id="bike529" depart="2254.67" from="378479743#5" to="-4195580#1" type="bike_bicycle"/>
    <trip id="bike530" depart="2257.99" from="700440148" to="23508141#1" type="bike_bicycle"/>
    <trip id="bike531" depart="2260.39" from="53207959#0" to="116556688" type="bike_bicycle"/>
    <trip id="bike532" depart="2260.66" from="23508141#1" to="-881694399" type="bike_bicycle"/>
    <trip id="bike533" depart="2261.68" from="-700440129" to="196656222#2" type="bike_bicycle"/>
    <trip id="bike534" depart="2266.25" from="196656222#2" to="-23015831" type="bike_bicycle"/>
    <trip id="bike535" depart="2266.67" from="75392301#1" to="150041579#2" type="bike_bicycle"/>
    <trip id="bike536" depart="2267.31" from="689912267#0" to="700440148" type="bike_bicycle"/>
    <trip id="bike537" depart="2268.23" from="1265069359" to="150032770#0" type="bike_bicycle"/>
    <trip id="bike538" depart="2271.44" from="35574708#1" to="-4295817#1" type="bike_bicycle"/>
    <trip id="bike539" depart="2274.37" from="-378479743#5" to="-624481020#0" type="bike_bicycle"/>
    <trip id="bike540" depart="2276.45" from="715835444#1" to="254075881#1" type="bike_bicycle"/>
    <trip id="bike541" depart="2285.13" from="150032770#6" to="-378479743#4" type="bike_bicycle"/>
    <trip id="bike542" depart="2297.15" from="-881694399" to="116556686#1" type="bike_bicycle"/>
    <trip id="bike543" depart="2298.61" from="624481020#4" to="196656222#0" type="bike_bicycle"/>
    <trip id="bike544" depart="2306.52" from="4144040#1" to="4144040#4" type="bike_bicycle"/>
    <trip id="bike545" depart="2310.91" from="-700440128" to="624481020#1" type="bike_bicycle"/>
    <trip id="bike546" depart="2311.87" from="715913363#2" to="38115188" type="bike_bicycle"/>
    <trip id="bike547" depart="2315.80" from="196656222#1" to="-4144040#0" type="bike_bicycle"/>
    <trip id="bike548" depart="2318.06" from="59591195#0" to="-4144040#0" type="bike_bicycle"/>
    <trip id="bike549" depart="2323.86" from="43135644#0" to="150041594#0" type="bike_bicycle"/>
    <trip id="bike550" depart="2329.57" from="70205228#0" to="23508141#0" type="bike_bicycle"/>
    <trip id="bike551" depart="2331.76" from="4019053#2" to="-150041551#3" type="bike_bicycle"/>
    <trip id="bike552" depart="2333.25" from="-150032770#6" to="700236092#0" type="bike_bicycle"/>
    <trip id="bike553" depart="2338.10" from="715835444#3" to="4144040#1" type="bike_bicycle"/>
    <trip id="bike554" depart="2342.83" from="506015829#1" to="149518769#1" type="bike_bicycle"/>
    <trip id="bike555" depart="2356.78" from="689912267#0" to="-484022097" type="bike_bicycle"/>
    <trip id="bike556" depart="2357.69" from="4295817#1" to="-1265069360#0" type="bike_bicycle"/>
    <trip id="bike557" depart="2358.77" from="214812788#2" to="103958941#2" type="bike_bicycle"/>
    <trip id="bike558" depart="2363.29" from="38115188" to="4144040#1" type="bike_bicycle"/>
    <trip id="bike559" depart="2370.17" from="378479753" to="150041593" type="bike_bicycle"/>
    <trip id="bike560" depart="2371.08" from="196656222#0" to="-1265069360#0" type="bike_bicycle"/>
    <trip id="bike561" depart="2373.96" from="24509268" to="-1290085526#1" type="bike_bicycle"/>
    <trip id="bike562" depart="2375.29" from="23508141#0" to="-624481020#4" type="bike_bicycle"/>
    <trip id="bike563" depart="2375.59" from="75392301#0" to="-150032770#0" type="bike_bicycle"/>
    <trip id="bike564" depart="2378.65" from="60263960" to="4144040#2" type="bike_bicycle"/>
    <trip id="bike565" depart="2385.78" from="59591195#2" to="700440139" type="bike_bicycle"/>
    <trip id="bike566" depart="2388.35" from="-23508141#1" to="-23015831" type="bike_bicycle"/>
    <trip id="bike567" depart="2394.98" from="-378479743#5" to="-4144040#4" type="bike_bicycle"/>
    <trip id="bike568" depart="2397.92" from="23248109#1" to="59591195#2" type="bike_bicycle"/>
    <trip id="bike569" depart="2410.97" from="-700440130#0" to="1290085525#1" type="bike_bicycle"/>
    <trip id="bike570" depart="2414.22" from="1290085525#0" to="1290085526#0" type="bike_bicycle"/>
    <trip id="bike571" depart="2418.86" from="35574708#1" to="E0" type="bike_bicycle"/>
    <trip id="bike572" depart="2425.89" from="-56163443#3" to="4144040#4" type="bike_bicycle"/>
    <trip id="bike573" depart="2438.21" from="700236092#0" to="395456769#1" type="bike_bicycle"/>
    <trip id="bike574" depart="2441.52" from="700236093" to="492925919" type="bike_bicycle"/>
    <trip id="bike575" depart="2441.58" from="-23248109#0" to="116556686#1" type="bike_bicycle"/>
    <trip id="bike576" depart="2443.28" from="24509268" to="-150041551#3" type="bike_bicycle"/>
    <trip id="bike577" depart="2455.41" from="-1290085526#1" to="-4144040#0" type="bike_bicycle"/>
    <trip id="bike578" depart="2465.49" from="196656222#2" to="150032770#5" type="bike_bicycle"/>
    <trip id="bike579" depart="2470.08" from="53207959#3" to="23508224" type="bike_bicycle"/>
    <trip id="bike580" depart="2472.06" from="700236093" to="-23015831" type="bike_bicycle"/>
    <trip id="bike581" depart="2472.23" from="23508141#0" to="-150032770#6" type="bike_bicycle"/>
    <trip id="bike582" depart="2477.72" from="-484022097" to="700440129" type="bike_bicycle"/>
    <trip id="bike583" depart="2481.61" from="700440131" to="150041580" type="bike_bicycle"/>
    <trip id="bike584" depart="2484.39" from="-150041551#1" to="-182982119#1" type="bike_bicycle"/>
    <trip id="bike585" depart="2499.11" from="70205228#1" to="700440137" type="bike_bicycle"/>
    <trip id="bike586" depart="2509.16" from="35574708#1" to="-150032770#2" type="bike_bicycle"/>
    <trip id="bike587" depart="2521.01" from="70205228#2" to="-70205228#0" type="bike_bicycle"/>
    <trip id="bike588" depart="2521.79" from="715913363#2" to="378479740#1" type="bike_bicycle"/>
    <trip id="bike589" depart="2522.18" from="492925920#1" to="4195610#2" type="bike_bicycle"/>
    <trip id="bike590" depart="2533.31" from="150032770#0" to="-182982119#1" type="bike_bicycle"/>
    <trip id="bike591" depart="2533.48" from="-4144040#2" to="-53207957" type="bike_bicycle"/>
    <trip id="bike592" depart="2537.61" from="624481020#4" to="1265069358#1" type="bike_bicycle"/>
    <trip id="bike593" depart="2538.70" from="700440137" to="-715835444#1" type="bike_bicycle"/>
    <trip id="bike594" depart="2542.54" from="506013711#1" to="-378479743#2" type="bike_bicycle"/>
    <trip id="bike595" depart="2552.72" from="881694399" to="4295817#1" type="bike_bicycle"/>
    <trip id="bike596" depart="2560.95" from="214812786" to="75392301#0" type="bike_bicycle"/>
    <trip id="bike597" depart="2561.02" from="-150041551#3" to="150032770#6" type="bike_bicycle"/>
    <trip id="bike598" depart="2561.58" from="624481020#4" to="-715835444#2" type="bike_bicycle"/>
    <trip id="bike599" depart="2562.93" from="51873805" to="715835444#4" type="bike_bicycle"/>
    <trip id="bike600" depart="2567.13" from="150032770#0" to="506015829#1" type="bike_bicycle"/>
    <trip id="bike601" depart="2570.69" from="-150032770#5" to="-624481020#3" type="bike_bicycle"/>
    <trip id="bike602" depart="2580.25" from="E0" to="150041594#0" type="bike_bicycle"/>
    <trip id="bike603" depart="2585.23" from="1185215707" to="715835444#2" type="bike_bicycle"/>
    <trip id="bike604" depart="2592.83" from="150041551#1" to="4144040#3" type="bike_bicycle"/>
    <trip id="bike605" depart="2597.65" from="4144040#2" to="-196656222#1" type="bike_bicycle"/>
    <trip id="bike606" depart="2600.48" from="38115188" to="56163443#1" type="bike_bicycle"/>
    <trip id="bike607" depart="2600.84" from="4295817#3" to="-196656222#0" type="bike_bicycle"/>
    <trip id="bike608" depart="2603.46" from="-378479743#6" to="4195610#2" type="bike_bicycle"/>
    <trip id="bike609" depart="2609.06" from="395456769#1" to="449551311" type="bike_bicycle"/>
    <trip id="bike610" depart="2612.46" from="-715835444#4" to="-23248109#1" type="bike_bicycle"/>
    <trip id="bike611" depart="2612.65" from="-1265069358#1" to="-700440136" type="bike_bicycle"/>
    <trip id="bike612" depart="2619.52" from="1185215707" to="-624481020#3" type="bike_bicycle"/>
    <trip id="bike613" depart="2625.21" from="-378479743#2" to="-4144040#3" type="bike_bicycle"/>
    <trip id="bike614" depart="2627.95" from="150041578" to="23508142#0" type="bike_bicycle"/>
    <trip id="bike615" depart="2632.73" from="150032770#2" to="-150032770#1" type="bike_bicycle"/>
    <trip id="bike616" depart="2633.92" from="116556688" to="-196656222#2" type="bike_bicycle"/>
    <trip id="bike617" depart="2646.88" from="378479743#4" to="-70205228#2" type="bike_bicycle"/>
    <trip id="bike618" depart="2647.13" from="1290085526#0" to="-700440129" type="bike_bicycle"/>
    <trip id="bike619" depart="2659.90" from="1290085526#0" to="-196656222#1" type="bike_bicycle"/>
    <trip id="bike620" depart="2661.68" from="700440138" to="700440139" type="bike_bicycle"/>
    <trip id="bike621" depart="2661.90" from="75392301#1" to="24509268" type="bike_bicycle"/>
    <trip id="bike622" depart="2662.90" from="-4144040#3" to="116556688" type="bike_bicycle"/>
    <trip id="bike623" depart="2664.68" from="-378479743#3" to="-700440130#0" type="bike_bicycle"/>
    <trip id="bike624" depart="2668.69" from="196656222#1" to="-150041565" type="bike_bicycle"/>
    <trip id="bike625" depart="2681.24" from="150041551#2" to="150032770#1" type="bike_bicycle"/>
    <trip id="bike626" depart="2681.34" from="196656222#0" to="-182982119#1" type="bike_bicycle"/>
    <trip id="bike627" depart="2682.09" from="-689912267#0" to="-56163443#3" type="bike_bicycle"/>
    <trip id="bike628" depart="2692.29" from="395456768" to="378479743#0" type="bike_bicycle"/>
    <trip id="bike629" depart="2693.78" from="-4295817#0" to="-23248109#1" type="bike_bicycle"/>
    <trip id="bike630" depart="2703.16" from="-715835444#1" to="715835444#3" type="bike_bicycle"/>
    <trip id="bike631" depart="2708.26" from="-881694399" to="378479743#5" type="bike_bicycle"/>
    <trip id="bike632" depart="2708.27" from="59591195#1" to="-70205228#2" type="bike_bicycle"/>
    <trip id="bike633" depart="2713.49" from="103958941#0" to="59591195#2" type="bike_bicycle"/>
    <trip id="bike634" depart="2717.11" from="700236093" to="75392301#0" type="bike_bicycle"/>
    <trip id="bike635" depart="2717.52" from="-378479743#3" to="-70205228#1" type="bike_bicycle"/>
    <trip id="bike636" depart="2718.26" from="715835444#3" to="-4195580#0" type="bike_bicycle"/>
    <trip id="bike637" depart="2719.44" from="-715835444#3" to="715913363#2" type="bike_bicycle"/>
    <trip id="bike638" depart="2720.85" from="73372559" to="-700440129" type="bike_bicycle"/>
    <trip id="bike639" depart="2731.04" from="4195610#2" to="150041594#0" type="bike_bicycle"/>
    <trip id="bike640" depart="2735.01" from="378479743#0" to="-53207957" type="bike_bicycle"/>
    <trip id="bike641" depart="2739.89" from="1290085525#0" to="60263960" type="bike_bicycle"/>
    <trip id="bike642" depart="2740.52" from="149518769#1" to="-23508141#0" type="bike_bicycle"/>
    <trip id="bike643" depart="2742.79" from="35574708#1" to="378479743#0" type="bike_bicycle"/>
    <trip id="bike644" depart="2746.77" from="23508224" to="4144040#4" type="bike_bicycle"/>
    <trip id="bike645" depart="2751.21" from="24509268" to="715835444#4" type="bike_bicycle"/>
    <trip id="bike646" depart="2753.17" from="150041580" to="4195610#0" type="bike_bicycle"/>
    <trip id="bike647" depart="2753.92" from="150041551#2" to="-700440129" type="bike_bicycle"/>
    <trip id="bike648" depart="2755.32" from="4195610#0" to="60263960" type="bike_bicycle"/>
    <trip id="bike649" depart="2758.72" from="59591195#0" to="149518769#1" type="bike_bicycle"/>
    <trip id="bike650" depart="2764.82" from="196656222#2" to="378479753" type="bike_bicycle"/>
    <trip id="bike651" depart="2771.71" from="-624481020#3" to="395456769#1" type="bike_bicycle"/>
    <trip id="bike652" depart="2774.53" from="4295817#3" to="53207959#3" type="bike_bicycle"/>
    <trip id="bike653" depart="2786.09" from="-196656222#1" to="E0" type="bike_bicycle"/>
    <trip id="bike654" depart="2788.26" from="182982119#0" to="1290085525#1" type="bike_bicycle"/>
    <trip id="bike655" depart="2799.38" from="214812788#2" to="70205228#0" type="bike_bicycle"/>
    <trip id="bike656" depart="2802.63" from="4195610#0" to="23508141#0" type="bike_bicycle"/>
    <trip id="bike657" depart="2811.30" from="56163443#1" to="-881694399" type="bike_bicycle"/>
    <trip id="bike658" depart="2816.34" from="700440137" to="23248109#1" type="bike_bicycle"/>
    <trip id="bike659" depart="2818.69" from="395456769#1" to="-196656222#1" type="bike_bicycle"/>
    <trip id="bike660" depart="2823.76" from="51873805" to="395456769#1" type="bike_bicycle"/>
    <trip id="bike661" depart="2825.57" from="116556688" to="395456768" type="bike_bicycle"/>
    <trip id="bike662" depart="2826.65" from="-150041551#0" to="881694399" type="bike_bicycle"/>
    <trip id="bike663" depart="2827.41" from="4195580#0" to="1290085525#1" type="bike_bicycle"/>
    <trip id="bike664" depart="2830.90" from="492925920#1" to="715913363#2" type="bike_bicycle"/>
    <trip id="bike665" depart="2837.22" from="150041551#1" to="-1265069360#0" type="bike_bicycle"/>
    <trip id="bike666" depart="2842.50" from="-700440128" to="196656222#2" type="bike_bicycle"/>
    <trip id="bike667" depart="2848.51" from="23248109#0" to="254075881#1" type="bike_bicycle"/>
    <trip id="bike668" depart="2852.35" from="378479743#0" to="150041551#0" type="bike_bicycle"/>
    <trip id="bike669" depart="2855.64" from="149518769#1" to="506015829#1" type="bike_bicycle"/>
    <trip id="bike670" depart="2856.01" from="378479743#2" to="196656222#0" type="bike_bicycle"/>
    <trip id="bike671" depart="2856.06" from="116556686#1" to="-150032770#1" type="bike_bicycle"/>
    <trip id="bike672" depart="2860.20" from="-23508141#0" to="150032770#0" type="bike_bicycle"/>
    <trip id="bike673" depart="2871.61" from="715913363#2" to="-23508141#0" type="bike_bicycle"/>
    <trip id="bike674" depart="2872.48" from="715835444#2" to="-378479743#2" type="bike_bicycle"/>
    <trip id="bike675" depart="2878.69" from="-715835444#3" to="150041551#2" type="bike_bicycle"/>
    <trip id="bike676" depart="2883.27" from="-4295817#3" to="150041593" type="bike_bicycle"/>
    <trip id="bike677" depart="2888.56" from="150041594#0" to="150032770#6" type="bike_bicycle"/>
    <trip id="bike678" depart="2889.06" from="4195610#2" to="-70205228#1" type="bike_bicycle"/>
    <trip id="bike679" depart="2890.30" from="-715835444#1" to="59591195#2" type="bike_bicycle"/>
    <trip id="bike680" depart="2893.20" from="-23508224" to="700236092#1" type="bike_bicycle"/>
    <trip id="bike681" depart="2897.61" from="4144040#0" to="4144040#3" type="bike_bicycle"/>
    <trip id="bike682" depart="2899.93" from="-4144040#2" to="881694399" type="bike_bicycle"/>
    <trip id="bike683" depart="2900.69" from="-624481020#3" to="-4144040#1" type="bike_bicycle"/>
    <trip id="bike684" depart="2907.95" from="-4144040#1" to="23508142#1" type="bike_bicycle"/>
    <trip id="bike685" depart="2915.86" from="715835444#5" to="-484022097" type="bike_bicycle"/>
    <trip id="bike686" depart="2920.76" from="150032770#1" to="-4144040#3" type="bike_bicycle"/>
    <trip id="bike687" depart="2922.49" from="4019053#2" to="150032770#5" type="bike_bicycle"/>
    <trip id="bike688" depart="2932.13" from="-150032770#5" to="378479743#3" type="bike_bicycle"/>
    <trip id="bike689" depart="2933.83" from="-4295817#0" to="378479743#0" type="bike_bicycle"/>
    <trip id="bike690" depart="2939.38" from="1290085526#0" to="4195610#0" type="bike_bicycle"/>
    <trip id="bike691" depart="2940.04" from="-4295817#3" to="484022097" type="bike_bicycle"/>
    <trip id="bike692" depart="2942.05" from="59591195#2" to="-150041565" type="bike_bicycle"/>
    <trip id="bike693" depart="2942.45" from="-23508141#0" to="700440130#0" type="bike_bicycle"/>
    <trip id="bike694" depart="2946.34" from="-4195580#1" to="-70205228#2" type="bike_bicycle"/>
    <trip id="bike695" depart="2946.92" from="150041579#2" to="-624481020#0" type="bike_bicycle"/>
    <trip id="bike696" depart="2947.70" from="700440128" to="23015831" type="bike_bicycle"/>
    <trip id="bike697" depart="2957.65" from="4019053#2" to="378479743#0" type="bike_bicycle"/>
    <trip id="bike698" depart="2959.77" from="378479753" to="378479740#1" type="bike_bicycle"/>
    <trip id="bike699" depart="2966.87" from="116556686#1" to="700236092#0" type="bike_bicycle"/>
    <trip id="bike700" depart="2966.93" from="38115188" to="59591195#2" type="bike_bicycle"/>
    <trip id="bike701" depart="2973.02" from="4295817#1" to="-700440130#0" type="bike_bicycle"/>
    <trip id="bike702" depart="2982.79" from="378479753" to="-196656222#1" type="bike_bicycle"/>
    <trip id="bike703" depart="2986.51" from="-378479743#3" to="-23508141#1" type="bike_bicycle"/>
    <trip id="bike704" depart="2988.13" from="-715835444#1" to="-4144040#2" type="bike_bicycle"/>
    <trip id="bike705" depart="2992.33" from="4195610#0" to="196656222#2" type="bike_bicycle"/>
    <trip id="bike706" depart="2994.12" from="150032770#6" to="-378479743#1" type="bike_bicycle"/>
    <trip id="bike707" depart="2997.73" from="1290085526#0" to="-4144040#3" type="bike_bicycle"/>
    <trip id="bike708" depart="2999.24" from="395456769#1" to="4195580#1" type="bike_bicycle"/>
    <trip id="bike709" depart="3005.37" from="4144040#0" to="E2" type="bike_bicycle"/>
    <trip id="bike710" depart="3008.45" from="24509268" to="150041594#0" type="bike_bicycle"/>
    <trip id="bike711" depart="3013.20" from="-378479743#4" to="-70205228#0" type="bike_bicycle"/>
    <trip id="bike712" depart="3016.58" from="150041579#0" to="-150041551#1" type="bike_bicycle"/>
    <trip id="bike713" depart="3016.70" from="1185215707" to="-1265069360#0" type="bike_bicycle"/>
    <trip id="bike714" depart="3018.17" from="-378479743#3" to="59591195#2" type="bike_bicycle"/>
    <trip id="bike715" depart="3025.99" from="715913363#2" to="196656222#1" type="bike_bicycle"/>
    <trip id="bike716" depart="3031.20" from="196656222#2" to="4144040#4" type="bike_bicycle"/>
    <trip id="bike717" depart="3040.64" from="150032770#5" to="689912267#0" type="bike_bicycle"/>
    <trip id="bike718" depart="3050.09" from="196656222#0" to="-196656222#0" type="bike_bicycle"/>
    <trip id="bike719" depart="3051.61" from="-150032770#5" to="492925920#1" type="bike_bicycle"/>
    <trip id="bike720" depart="3052.41" from="-70205228#1" to="-624481020#4" type="bike_bicycle"/>
    <trip id="bike721" depart="3055.82" from="23508141#1" to="-4144040#0" type="bike_bicycle"/>
    <trip id="bike722" depart="3056.48" from="150041579#2" to="449551311" type="bike_bicycle"/>
    <trip id="bike723" depart="3057.31" from="506015829#1" to="23508141#1" type="bike_bicycle"/>
    <trip id="bike724" depart="3058.37" from="-23508224" to="-23508141#0" type="bike_bicycle"/>
    <trip id="bike725" depart="3059.72" from="53207959#0" to="624481020#1" type="bike_bicycle"/>
    <trip id="bike726" depart="3061.15" from="1265069359" to="624481020#1" type="bike_bicycle"/>
    <trip id="bike727" depart="3063.02" from="-150041551#0" to="4295817#0" type="bike_bicycle"/>
    <trip id="bike728" depart="3064.76" from="23508224" to="E0" type="bike_bicycle"/>
    <trip id="bike729" depart="3067.20" from="-23508141#0" to="624481020#2" type="bike_bicycle"/>
    <trip id="bike730" depart="3075.95" from="492925920#1" to="-700440130#0" type="bike_bicycle"/>
    <trip id="bike731" depart="3079.67" from="E2" to="150041551#1" type="bike_bicycle"/>
    <trip id="bike732" depart="3083.86" from="116556686#1" to="60263960" type="bike_bicycle"/>
    <trip id="bike733" depart="3086.84" from="150041565" to="E0" type="bike_bicycle"/>
    <trip id="bike734" depart="3086.92" from="53207959#0" to="-51873805" type="bike_bicycle"/>
    <trip id="bike735" depart="3089.31" from="59591195#2" to="378479740#1" type="bike_bicycle"/>
    <trip id="bike736" depart="3093.02" from="116556688" to="4195610#2" type="bike_bicycle"/>
    <trip id="bike737" depart="3093.79" from="395456769#0" to="-378479743#6" type="bike_bicycle"/>
    <trip id="bike738" depart="3094.09" from="-378479743#4" to="-4195580#1" type="bike_bicycle"/>
    <trip id="bike739" depart="3097.29" from="-4295817#3" to="-150041551#3" type="bike_bicycle"/>
    <trip id="bike740" depart="3098.16" from="116556688" to="-689912267#0" type="bike_bicycle"/>
    <trip id="bike741" depart="3108.11" from="23508141#1" to="-70205228#1" type="bike_bicycle"/>
    <trip id="bike742" depart="3110.58" from="4295817#0" to="-700440128" type="bike_bicycle"/>
    <trip id="bike743" depart="3112.45" from="-700440130#0" to="700236093" type="bike_bicycle"/>
    <trip id="bike744" depart="3114.10" from="881694399" to="4144040#3" type="bike_bicycle"/>
    <trip id="bike745" depart="3115.05" from="-23248109#1" to="715913363#2" type="bike_bicycle"/>
    <trip id="bike746" depart="3117.13" from="53207959#3" to="70205228#0" type="bike_bicycle"/>
    <trip id="bike747" depart="3124.54" from="E0" to="700440129" type="bike_bicycle"/>
    <trip id="bike748" depart="3136.80" from="-378479743#1" to="700440129" type="bike_bicycle"/>
    <trip id="bike749" depart="3143.27" from="-624481020#4" to="4195610#2" type="bike_bicycle"/>
    <trip id="bike750" depart="3147.13" from="624481020#2" to="492925920#1" type="bike_bicycle"/>
    <trip id="bike751" depart="3153.50" from="4195580#0" to="150041594#0" type="bike_bicycle"/>
    <trip id="bike752" depart="3154.39" from="378479743#0" to="-624481020#3" type="bike_bicycle"/>
    <trip id="bike753" depart="3158.92" from="150032770#5" to="150041551#1" type="bike_bicycle"/>
    <trip id="bike754" depart="3164.09" from="395456769#1" to="700440130#1" type="bike_bicycle"/>
    <trip id="bike755" depart="3166.08" from="-23248109#0" to="214812786" type="bike_bicycle"/>
    <trip id="bike756" depart="3176.96" from="-700440136" to="715835444#1" type="bike_bicycle"/>
    <trip id="bike757" depart="3177.13" from="1265069359" to="715835444#4" type="bike_bicycle"/>
    <trip id="bike758" depart="3177.69" from="-715835444#5" to="-1265069358#1" type="bike_bicycle"/>
    <trip id="bike759" depart="3185.16" from="53207959#0" to="43135644#0" type="bike_bicycle"/>
    <trip id="bike760" depart="3187.51" from="44973978" to="150041578" type="bike_bicycle"/>
    <trip id="bike761" depart="3188.24" from="4144040#3" to="-881694399" type="bike_bicycle"/>
    <trip id="bike762" depart="3189.10" from="-182982119#1" to="23248109#0" type="bike_bicycle"/>
    <trip id="bike763" depart="3195.97" from="-53207957" to="150032770#2" type="bike_bicycle"/>
    <trip id="bike764" depart="3199.98" from="-484022097" to="-624481020#3" type="bike_bicycle"/>
    <trip id="bike765" depart="3201.44" from="624481020#2" to="-715835444#2" type="bike_bicycle"/>
    <trip id="bike766" depart="3204.39" from="378479743#1" to="23508224" type="bike_bicycle"/>
    <trip id="bike767" depart="3205.87" from="196656222#0" to="-715835444#3" type="bike_bicycle"/>
    <trip id="bike768" depart="3211.07" from="4195580#1" to="-150041551#0" type="bike_bicycle"/>
    <trip id="bike769" depart="3213.09" from="-23248109#1" to="53207959#1" type="bike_bicycle"/>
    <trip id="bike770" depart="3221.03" from="150041579#2" to="-23508224" type="bike_bicycle"/>
    <trip id="bike771" depart="3221.62" from="700236093" to="150032770#6" type="bike_bicycle"/>
    <trip id="bike772" depart="3225.58" from="-1265069358#1" to="715835444#5" type="bike_bicycle"/>
    <trip id="bike773" depart="3226.20" from="-4295817#1" to="4195580#0" type="bike_bicycle"/>
    <trip id="bike774" depart="3226.73" from="-378479743#2" to="395456769#0" type="bike_bicycle"/>
    <trip id="bike775" depart="3235.29" from="-4144040#1" to="70205228#2" type="bike_bicycle"/>
    <trip id="bike776" depart="3238.94" from="-700440130#1" to="395456769#1" type="bike_bicycle"/>
    <trip id="bike777" depart="3244.53" from="-689912267#0" to="103958941#2" type="bike_bicycle"/>
    <trip id="bike778" depart="3246.42" from="700440138" to="-378479743#6" type="bike_bicycle"/>
    <trip id="bike779" depart="3260.05" from="150032770#0" to="-700440130#1" type="bike_bicycle"/>
    <trip id="bike780" depart="3260.68" from="4195610#2" to="-484022097" type="bike_bicycle"/>
    <trip id="bike781" depart="3261.37" from="4144040#1" to="4195580#2" type="bike_bicycle"/>
    <trip id="bike782" depart="3261.63" from="-1265069358#1" to="150041580" type="bike_bicycle"/>
    <trip id="bike783" depart="3267.57" from="-378479743#2" to="-4295817#3" type="bike_bicycle"/>
    <trip id="bike784" depart="3269.20" from="4195580#1" to="-1265069360#0" type="bike_bicycle"/>
    <trip id="bike785" depart="3273.27" from="4195610#2" to="60263960" type="bike_bicycle"/>
    <trip id="bike786" depart="3276.24" from="881694399" to="150032770#1" type="bike_bicycle"/>
    <trip id="bike787" depart="3279.48" from="-378479743#2" to="-150041594#1" type="bike_bicycle"/>
    <trip id="bike788" depart="3284.53" from="1290085525#1" to="4295817#3" type="bike_bicycle"/>
    <trip id="bike789" depart="3285.85" from="-23508141#0" to="-70205228#0" type="bike_bicycle"/>
    <trip id="bike790" depart="3293.23" from="700440130#1" to="-378479743#1" type="bike_bicycle"/>
    <trip id="bike791" depart="3295.69" from="53207959#0" to="484022097" type="bike_bicycle"/>
    <trip id="bike792" depart="3295.80" from="-378479743#2" to="E0" type="bike_bicycle"/>
    <trip id="bike793" depart="3297.47" from="-378479743#4" to="23015831" type="bike_bicycle"/>
    <trip id="bike794" depart="3299.67" from="-1290085526#1" to="395456769#0" type="bike_bicycle"/>
    <trip id="bike795" depart="3303.53" from="150041565" to="4295817#1" type="bike_bicycle"/>
    <trip id="bike796" depart="3303.71" from="395456769#0" to="-378479743#4" type="bike_bicycle"/>
    <trip id="bike797" depart="3305.83" from="150032770#5" to="4144040#4" type="bike_bicycle"/>
    <trip id="bike798" depart="3305.93" from="700236093" to="-196656222#1" type="bike_bicycle"/>
    <trip id="bike799" depart="3307.37" from="-23508141#0" to="484022097" type="bike_bicycle"/>
    <trip id="bike800" depart="3320.10" from="378479743#3" to="116556688" type="bike_bicycle"/>
    <trip id="bike801" depart="3322.25" from="715913363#2" to="-70205228#0" type="bike_bicycle"/>
    <trip id="bike802" depart="3332.43" from="-378479743#4" to="-624481020#4" type="bike_bicycle"/>
    <trip id="bike803" depart="3342.11" from="-23015831" to="23508142#0" type="bike_bicycle"/>
    <trip id="bike804" depart="3344.56" from="378479743#5" to="378479743#2" type="bike_bicycle"/>
    <trip id="bike805" depart="3352.28" from="53207959#1" to="4195580#0" type="bike_bicycle"/>
    <trip id="bike806" depart="3355.29" from="700236092#0" to="395456769#1" type="bike_bicycle"/>
    <trip id="bike807" depart="3360.54" from="-715835444#1" to="214812786" type="bike_bicycle"/>
    <trip id="bike808" depart="3361.08" from="214812788#2" to="44973978" type="bike_bicycle"/>
    <trip id="bike809" depart="3366.94" from="-70205228#2" to="-150041551#1" type="bike_bicycle"/>
    <trip id="bike810" depart="3368.23" from="700440137" to="715835444#4" type="bike_bicycle"/>
    <trip id="bike811" depart="3368.54" from="196656222#2" to="-23508141#0" type="bike_bicycle"/>
    <trip id="bike812" depart="3374.26" from="196656222#2" to="378479743#0" type="bike_bicycle"/>
    <trip id="bike813" depart="3377.92" from="23508141#0" to="75392301#1" type="bike_bicycle"/>
    <trip id="bike814" depart="3378.43" from="881694399" to="715835444#1" type="bike_bicycle"/>
    <trip id="bike815" depart="3385.92" from="-378479743#2" to="700440128" type="bike_bicycle"/>
    <trip id="bike816" depart="3394.35" from="378479740#1" to="103958941#0" type="bike_bicycle"/>
    <trip id="bike817" depart="3397.87" from="4195580#1" to="492925920#1" type="bike_bicycle"/>
    <trip id="bike818" depart="3399.85" from="715835444#4" to="506013711#1" type="bike_bicycle"/>
    <trip id="bike819" depart="3402.34" from="-150032770#1" to="-150041594#1" type="bike_bicycle"/>
    <trip id="bike820" depart="3402.66" from="-700440129" to="-150032770#6" type="bike_bicycle"/>
    <trip id="bike821" depart="3406.54" from="-150041594#1" to="53207959#3" type="bike_bicycle"/>
    <trip id="bike822" depart="3407.64" from="214812788#2" to="378479743#6" type="bike_bicycle"/>
    <trip id="bike823" depart="3408.03" from="214812786" to="150032770#0" type="bike_bicycle"/>
    <trip id="bike824" depart="3410.59" from="4295817#0" to="-196656222#0" type="bike_bicycle"/>
    <trip id="bike825" depart="3411.70" from="23508141#1" to="378479743#4" type="bike_bicycle"/>
    <trip id="bike826" depart="3414.22" from="-700440130#1" to="-700440136" type="bike_bicycle"/>
    <trip id="bike827" depart="3418.87" from="23015831" to="-4195580#1" type="bike_bicycle"/>
    <trip id="bike828" depart="3424.95" from="59591195#2" to="23248109#1" type="bike_bicycle"/>
    <trip id="bike829" depart="3430.78" from="149518769#1" to="378479753" type="bike_bicycle"/>
    <trip id="bike830" depart="3440.81" from="624481020#4" to="4144040#3" type="bike_bicycle"/>
    <trip id="bike831" depart="3442.65" from="-182982119#1" to="4195580#2" type="bike_bicycle"/>
    <trip id="bike832" depart="3447.44" from="44973978" to="700236092#0" type="bike_bicycle"/>
    <trip id="bike833" depart="3455.65" from="-150041594#1" to="-196656222#1" type="bike_bicycle"/>
    <trip id="bike834" depart="3461.84" from="150041551#2" to="150041551#2" type="bike_bicycle"/>
    <trip id="bike835" depart="3462.61" from="378479743#6" to="-700440136" type="bike_bicycle"/>
    <trip id="bike836" depart="3465.13" from="492925919" to="449551311" type="bike_bicycle"/>
    <trip id="bike837" depart="3471.81" from="-378479743#0" to="4195610#0" type="bike_bicycle"/>
    <trip id="bike838" depart="3479.00" from="4295817#0" to="-378479743#6" type="bike_bicycle"/>
    <trip id="bike839" depart="3480.83" from="715835444#4" to="214812788#2" type="bike_bicycle"/>
    <trip id="bike840" depart="3485.62" from="53207959#1" to="4295817#1" type="bike_bicycle"/>
    <trip id="bike841" depart="3487.97" from="-4144040#3" to="-23508224" type="bike_bicycle"/>
    <trip id="bike842" depart="3488.11" from="53207959#1" to="-624481020#3" type="bike_bicycle"/>
    <trip id="bike843" depart="3488.93" from="700440131" to="506015829#1" type="bike_bicycle"/>
    <trip id="bike844" depart="3491.87" from="-150032770#5" to="59591195#1" type="bike_bicycle"/>
    <trip id="bike845" depart="3492.42" from="-700440130#0" to="-150041565" type="bike_bicycle"/>
    <trip id="bike846" depart="3495.20" from="4295817#3" to="254075881#1" type="bike_bicycle"/>
    <trip id="bike847" depart="3495.56" from="-196656222#1" to="150041551#2" type="bike_bicycle"/>
    <trip id="bike848" depart="3509.56" from="1185215707" to="196656222#0" type="bike_bicycle"/>
    <trip id="bike849" depart="3516.03" from="378479740#1" to="103958941#0" type="bike_bicycle"/>
    <trip id="bike850" depart="3519.48" from="-689912267#0" to="-23248109#0" type="bike_bicycle"/>
    <trip id="bike851" depart="3520.79" from="378479743#0" to="4295817#1" type="bike_bicycle"/>
    <trip id="bike852" depart="3521.96" from="-60263960" to="196656222#2" type="bike_bicycle"/>
    <trip id="bike853" depart="3523.42" from="-150041551#0" to="700440128" type="bike_bicycle"/>
    <trip id="bike854" depart="3523.72" from="-624481020#4" to="150041579#2" type="bike_bicycle"/>
    <trip id="bike855" depart="3525.00" from="1290085525#1" to="-378479743#3" type="bike_bicycle"/>
    <trip id="bike856" depart="3528.03" from="70205228#2" to="700236093" type="bike_bicycle"/>
    <trip id="bike857" depart="3528.84" from="24509268" to="700440148" type="bike_bicycle"/>
    <trip id="bike858" depart="3529.11" from="492925919" to="150032770#1" type="bike_bicycle"/>
    <trip id="bike859" depart="3530.46" from="-715835444#4" to="150032770#0" type="bike_bicycle"/>
    <trip id="bike860" depart="3539.26" from="43135644#0" to="-624481020#3" type="bike_bicycle"/>
    <trip id="bike861" depart="3539.32" from="-196656222#2" to="103958941#2" type="bike_bicycle"/>
    <trip id="bike862" depart="3541.71" from="214812786" to="700440138" type="bike_bicycle"/>
    <trip id="bike863" depart="3541.75" from="-4195580#0" to="59591195#0" type="bike_bicycle"/>
    <trip id="bike864" depart="3542.18" from="75392301#1" to="715835444#4" type="bike_bicycle"/>
    <trip id="bike865" depart="3543.87" from="-196656222#0" to="150041579#0" type="bike_bicycle"/>
    <trip id="bike866" depart="3560.77" from="-700440136" to="700236092#0" type="bike_bicycle"/>
    <trip id="bike867" depart="3561.14" from="-715835444#5" to="23508142#0" type="bike_bicycle"/>
    <trip id="bike868" depart="3566.62" from="-1290085526#1" to="-4195580#0" type="bike_bicycle"/>
    <trip id="bike869" depart="3568.16" from="35574708#1" to="-700440130#1" type="bike_bicycle"/>
    <trip id="bike870" depart="3572.81" from="395456768" to="150041579#0" type="bike_bicycle"/>
    <trip id="bike871" depart="3573.78" from="378479743#3" to="182982119#0" type="bike_bicycle"/>
    <trip id="bike872" depart="3581.77" from="53207959#0" to="-4144040#4" type="bike_bicycle"/>
    <trip id="bike873" depart="3582.05" from="700440138" to="492925920#1" type="bike_bicycle"/>
    <trip id="bike874" depart="3589.38" from="-624481020#4" to="-1265069360#0" type="bike_bicycle"/>
    <trip id="bike875" depart="3596.16" from="150032770#2" to="-484022097" type="bike_bicycle"/>
    <trip id="bike876" depart="3596.52" from="116556686#1" to="689912267#0" type="bike_bicycle"/>
</routes>
